<annotation>
	<folder>D:/vscode_work/yolov7-main/detect_auto/images</folder>
	<filename>AfterConvert_RGB0_1483_3.png</filename>
	<path>D:/vscode_work/yolov7-main/detect_auto/images/AfterConvert_RGB0_1483_3.png</path>
	<source>
		<database>Unknown</database>
	</source>
	<size>
		<width>1280</width>
		<height>1024</height>
		<depth>3</depth>
	</size>
	<segmented>0</segmented>
	<object>
		<name>chick</name>
		<pose>Unspecified</pose>
		<truncated>0</truncated>
		<difficult>0</difficult>
		<bndbox>
			<xmin>1174</xmin>
			<ymin>861</ymin>
			<xmax>1280</xmax>
			<ymax>1012</ymax>
		</bndbox>
	</object>
	<object>
		<name>chick</name>
		<pose>Unspecified</pose>
		<truncated>0</truncated>
		<difficult>0</difficult>
		<bndbox>
			<xmin>448</xmin>
			<ymin>0</ymin>
			<xmax>586</xmax>
			<ymax>59</ymax>
		</bndbox>
	</object>
	<object>
		<name>chick</name>
		<pose>Unspecified</pose>
		<truncated>0</truncated>
		<difficult>0</difficult>
		<bndbox>
			<xmin>680</xmin>
			<ymin>303</ymin>
			<xmax>822</xmax>
			<ymax>447</ymax>
		</bndbox>
	</object>
	<object>
		<name>chick</name>
		<pose>Unspecified</pose>
		<truncated>0</truncated>
		<difficult>0</difficult>
		<bndbox>
			<xmin>554</xmin>
			<ymin>167</ymin>
			<xmax>666</xmax>
			<ymax>280</ymax>
		</bndbox>
	</object>
</annotation>