<annotation>
	<folder>D:/vscode_work/yolov7-main/detect_auto/images</folder>
	<filename>AfterConvert_RGB0_1311_3.png</filename>
	<path>D:/vscode_work/yolov7-main/detect_auto/images/AfterConvert_RGB0_1311_3.png</path>
	<source>
		<database>Unknown</database>
	</source>
	<size>
		<width>1280</width>
		<height>1024</height>
		<depth>3</depth>
	</size>
	<segmented>0</segmented>
	<object>
		<name>chick</name>
		<pose>Unspecified</pose>
		<truncated>0</truncated>
		<difficult>0</difficult>
		<bndbox>
			<xmin>313</xmin>
			<ymin>0</ymin>
			<xmax>438</xmax>
			<ymax>73</ymax>
		</bndbox>
	</object>
	<object>
		<name>chick</name>
		<pose>Unspecified</pose>
		<truncated>0</truncated>
		<difficult>0</difficult>
		<bndbox>
			<xmin>920</xmin>
			<ymin>18</ymin>
			<xmax>1036</xmax>
			<ymax>117</ymax>
		</bndbox>
	</object>
</annotation>