<annotation>
	<folder>D:/vscode_work/yolov7-main/detect_auto/images</folder>
	<filename>Video_20221101153118476_138.png</filename>
	<path>D:/vscode_work/yolov7-main/detect_auto/images/Video_20221101153118476_138.png</path>
	<source>
		<database>Unknown</database>
	</source>
	<size>
		<width>1280</width>
		<height>1024</height>
		<depth>3</depth>
	</size>
	<segmented>0</segmented>
	<object>
		<name>chick</name>
		<pose>Unspecified</pose>
		<truncated>0</truncated>
		<difficult>0</difficult>
		<bndbox>
			<xmin>433</xmin>
			<ymin>9</ymin>
			<xmax>590</xmax>
			<ymax>143</ymax>
		</bndbox>
	</object>
	<object>
		<name>chick</name>
		<pose>Unspecified</pose>
		<truncated>0</truncated>
		<difficult>0</difficult>
		<bndbox>
			<xmin>632</xmin>
			<ymin>184</ymin>
			<xmax>764</xmax>
			<ymax>310</ymax>
		</bndbox>
	</object>
	<object>
		<name>chick</name>
		<pose>Unspecified</pose>
		<truncated>0</truncated>
		<difficult>0</difficult>
		<bndbox>
			<xmin>448</xmin>
			<ymin>303</ymin>
			<xmax>567</xmax>
			<ymax>449</ymax>
		</bndbox>
	</object>
	<object>
		<name>chick</name>
		<pose>Unspecified</pose>
		<truncated>0</truncated>
		<difficult>0</difficult>
		<bndbox>
			<xmin>1</xmin>
			<ymin>392</ymin>
			<xmax>100</xmax>
			<ymax>501</ymax>
		</bndbox>
	</object>
</annotation>