<annotation>
	<folder>D:/vscode_work/yolov7-main/detect_auto/images</folder>
	<filename>Video_20221101153118476_221.png</filename>
	<path>D:/vscode_work/yolov7-main/detect_auto/images/Video_20221101153118476_221.png</path>
	<source>
		<database>Unknown</database>
	</source>
	<size>
		<width>1280</width>
		<height>1024</height>
		<depth>3</depth>
	</size>
	<segmented>0</segmented>
	<object>
		<name>chick</name>
		<pose>Unspecified</pose>
		<truncated>0</truncated>
		<difficult>0</difficult>
		<bndbox>
			<xmin>160</xmin>
			<ymin>294</ymin>
			<xmax>309</xmax>
			<ymax>432</ymax>
		</bndbox>
	</object>
	<object>
		<name>chick</name>
		<pose>Unspecified</pose>
		<truncated>0</truncated>
		<difficult>0</difficult>
		<bndbox>
			<xmin>475</xmin>
			<ymin>244</ymin>
			<xmax>606</xmax>
			<ymax>365</ymax>
		</bndbox>
	</object>
</annotation>